{
  "pythia-70m": {
    "num_layers": 6,
    "M": 18,
    "total_product": 59682507274.15424,
    "geomean": 3.968790458981253,
    "median_sigma": 6.9199434487611935,
    "min_sigma": 0.8294833462077322,
    "max_sigma": 23.17327403900832,
    "num_below_1_5": 7,
    "product_below_1_5": 1.0101714562796995,
    "prod_attn": 37638.075588474756,
    "prod_mlp": 10.438662244130219,
    "prod_block": 151905.95657275055,
    "gm_attn": 5.789013580087243,
    "gm_mlp": 1.4783393635038033,
    "gm_block": 7.304589264030626,
    "per_layer": [
      {
        "layer": 0,
        "sigma_attn": 7.49094040819583,
        "sigma_mlp": 6.9199434487611935,
        "sigma_block": 10.917954416546753
      },
      {
        "layer": 1,
        "sigma_attn": 0.8699568073513296,
        "sigma_mlp": 0.9492393442336553,
        "sigma_block": 1.5583653902947725
      },
      {
        "layer": 2,
        "sigma_attn": 0.9540855019630081,
        "sigma_mlp": 0.8294833462077322,
        "sigma_block": 1.451864306850076
      },
      {
        "layer": 3,
        "sigma_attn": 12.890734481001578,
        "sigma_mlp": 0.9645149890527902,
        "sigma_block": 12.943589301783287
      },
      {
        "layer": 4,
        "sigma_attn": 23.135112942920955,
        "sigma_mlp": 1.103803315443242,
        "sigma_block": 23.17327403900832
      },
      {
        "layer": 5,
        "sigma_attn": 20.298165706621653,
        "sigma_mlp": 1.7995264040685395,
        "sigma_block": 20.501993066401006
      }
    ]
  },
  "pythia-160m": {
    "num_layers": 12,
    "M": 36,
    "total_product": 2.6460719126965828e+16,
    "geomean": 2.858797403418679,
    "median_sigma": 3.7567092275719474,
    "min_sigma": 0.5952763802947668,
    "max_sigma": 15.240501006120109,
    "num_below_1_5": 15,
    "product_below_1_5": 0.04923284675633021,
    "prod_attn": 63094708.44995952,
    "prod_mlp": 0.6245551477881426,
    "prod_block": 671487469.3569288,
    "gm_attn": 4.466829868539508,
    "gm_mlp": 0.9615330858828747,
    "gm_block": 5.439844591694455,
    "per_layer": [
      {
        "layer": 0,
        "sigma_attn": 7.358764678004212,
        "sigma_mlp": 8.580667321619606,
        "sigma_block": 12.208446211302498
      },
      {
        "layer": 1,
        "sigma_attn": 0.6123638352427837,
        "sigma_mlp": 0.7610490516675951,
        "sigma_block": 1.4077533159867832
      },
      {
        "layer": 2,
        "sigma_attn": 0.5952763802947668,
        "sigma_mlp": 0.831579123840352,
        "sigma_block": 1.31810642327436
      },
      {
        "layer": 3,
        "sigma_attn": 2.4162434625839153,
        "sigma_mlp": 0.7364947112490757,
        "sigma_block": 2.6253943831129107
      },
      {
        "layer": 4,
        "sigma_attn": 3.63799028151634,
        "sigma_mlp": 0.6521143626799922,
        "sigma_block": 3.7567092275719474
      },
      {
        "layer": 5,
        "sigma_attn": 5.640126242371359,
        "sigma_mlp": 0.7000955990123143,
        "sigma_block": 5.72842168875022
      },
      {
        "layer": 6,
        "sigma_attn": 4.92747313182793,
        "sigma_mlp": 0.6575458010296559,
        "sigma_block": 5.031276194864051
      },
      {
        "layer": 7,
        "sigma_attn": 5.57881366154948,
        "sigma_mlp": 0.7241550367292906,
        "sigma_block": 5.68879174873865
      },
      {
        "layer": 8,
        "sigma_attn": 15.197178009290104,
        "sigma_mlp": 0.7966987445251863,
        "sigma_block": 15.240501006120109
      },
      {
        "layer": 9,
        "sigma_attn": 12.374386565503608,
        "sigma_mlp": 0.8023065628505872,
        "sigma_block": 12.433787022921134
      },
      {
        "layer": 10,
        "sigma_attn": 12.38230878988335,
        "sigma_mlp": 0.7881161258121792,
        "sigma_block": 12.445728040876656
      },
      {
        "layer": 11,
        "sigma_attn": 7.411641527658065,
        "sigma_mlp": 1.4259375286523746,
        "sigma_block": 7.772168368041877
      }
    ]
  },
  "pythia-410m": {
    "num_layers": 24,
    "M": 72,
    "total_product": 0.6196452601558627,
    "geomean": 0.9933747095791434,
    "median_sigma": 0.7128786973477965,
    "min_sigma": 0.3131997592049414,
    "max_sigma": 14.233217518954996,
    "num_below_1_5": 55,
    "product_below_1_5": 1.1185190652438989e-12,
    "prod_attn": 0.09137083607104568,
    "prod_mlp": 4.342678288371027e-06,
    "prod_block": 1561629.0371432272,
    "gm_attn": 0.9051078188891563,
    "gm_mlp": 0.5978238481155543,
    "gm_block": 1.8116143195583374,
    "per_layer": [
      {
        "layer": 0,
        "sigma_attn": 6.173929463705797,
        "sigma_mlp": 11.545054279071683,
        "sigma_block": 14.233217518954996
      },
      {
        "layer": 1,
        "sigma_attn": 0.5516400768287646,
        "sigma_mlp": 0.49582075195395026,
        "sigma_block": 1.2699654571058692
      },
      {
        "layer": 2,
        "sigma_attn": 0.3131997592049414,
        "sigma_mlp": 0.7128786973477965,
        "sigma_block": 1.2762835448424867
      },
      {
        "layer": 3,
        "sigma_attn": 0.38844624562945,
        "sigma_mlp": 0.6712307151815473,
        "sigma_block": 1.1667028947251548
      },
      {
        "layer": 4,
        "sigma_attn": 0.3354947152828125,
        "sigma_mlp": 0.6912024022482919,
        "sigma_block": 1.166236012529773
      },
      {
        "layer": 5,
        "sigma_attn": 0.4716226673286581,
        "sigma_mlp": 0.731256240219184,
        "sigma_block": 1.1003403013040434
      },
      {
        "layer": 6,
        "sigma_attn": 0.3520106795198605,
        "sigma_mlp": 0.5667234277485225,
        "sigma_block": 1.080316068195271
      },
      {
        "layer": 7,
        "sigma_attn": 0.38150283670380347,
        "sigma_mlp": 0.5292417202162374,
        "sigma_block": 1.006388297274742
      },
      {
        "layer": 8,
        "sigma_attn": 0.3521092209739407,
        "sigma_mlp": 0.5402083228118901,
        "sigma_block": 0.9835652068999275
      },
      {
        "layer": 9,
        "sigma_attn": 0.31505451705119875,
        "sigma_mlp": 0.510431583631322,
        "sigma_block": 0.9609493885797799
      },
      {
        "layer": 10,
        "sigma_attn": 0.3300906570578676,
        "sigma_mlp": 0.5020018939315737,
        "sigma_block": 0.963904912692156
      },
      {
        "layer": 11,
        "sigma_attn": 0.41248107696548636,
        "sigma_mlp": 0.5315735564910955,
        "sigma_block": 0.9662824881545091
      },
      {
        "layer": 12,
        "sigma_attn": 0.31427787829512627,
        "sigma_mlp": 0.49960313342828144,
        "sigma_block": 0.96826948335386
      },
      {
        "layer": 13,
        "sigma_attn": 0.5378785406027146,
        "sigma_mlp": 0.49598003513993205,
        "sigma_block": 1.0927532980078971
      },
      {
        "layer": 14,
        "sigma_attn": 1.0465315023074162,
        "sigma_mlp": 0.4572808418859749,
        "sigma_block": 1.4143818706073457
      },
      {
        "layer": 15,
        "sigma_attn": 0.6066155509103577,
        "sigma_mlp": 0.47597812478941376,
        "sigma_block": 1.140241615772043
      },
      {
        "layer": 16,
        "sigma_attn": 0.3148095764389436,
        "sigma_mlp": 0.4964551056475634,
        "sigma_block": 1.0310370204149937
      },
      {
        "layer": 17,
        "sigma_attn": 2.1276880474898645,
        "sigma_mlp": 0.48230891384764735,
        "sigma_block": 2.3569099136772684
      },
      {
        "layer": 18,
        "sigma_attn": 3.9209170857125186,
        "sigma_mlp": 0.46025106266837196,
        "sigma_block": 4.060500530002721
      },
      {
        "layer": 19,
        "sigma_attn": 5.059331835437921,
        "sigma_mlp": 0.45652723900827086,
        "sigma_block": 5.172623940785209
      },
      {
        "layer": 20,
        "sigma_attn": 4.587183606883366,
        "sigma_mlp": 0.43071929573635803,
        "sigma_block": 4.713442756929651
      },
      {
        "layer": 21,
        "sigma_attn": 5.329657277758696,
        "sigma_mlp": 0.44804099762763927,
        "sigma_block": 5.439960028603433
      },
      {
        "layer": 22,
        "sigma_attn": 4.941370560123465,
        "sigma_mlp": 0.47002789001085044,
        "sigma_block": 5.071687144777104
      },
      {
        "layer": 23,
        "sigma_attn": 3.9885039231844543,
        "sigma_mlp": 0.5774575945280647,
        "sigma_block": 4.170878314697193
      }
    ]
  },
  "pythia-1b": {
    "num_layers": 16,
    "M": 48,
    "total_product": 3.5821834394528235e-08,
    "geomean": 0.6996455555005471,
    "median_sigma": 0.5691436734663207,
    "min_sigma": 0.21849192506699344,
    "max_sigma": 17.664599495410425,
    "num_below_1_5": 45,
    "product_below_1_5": 1.850771821305144e-11,
    "prod_attn": 2.402592726637512e-07,
    "prod_mlp": 0.002207678837226156,
    "prod_block": 67.53544553462775,
    "gm_attn": 0.38573807592552706,
    "gm_mlp": 0.6823323992418888,
    "gm_block": 1.301205036402775,
    "per_layer": [
      {
        "layer": 0,
        "sigma_attn": 8.07846530392476,
        "sigma_mlp": 13.56320368787487,
        "sigma_block": 17.664599495410425
      },
      {
        "layer": 1,
        "sigma_attn": 0.44377039642590044,
        "sigma_mlp": 0.4944089689031864,
        "sigma_block": 1.1878097320880838
      },
      {
        "layer": 2,
        "sigma_attn": 0.3594676204915125,
        "sigma_mlp": 0.6573240844163122,
        "sigma_block": 1.221201557153523
      },
      {
        "layer": 3,
        "sigma_attn": 0.4234075849001295,
        "sigma_mlp": 0.6794172085324799,
        "sigma_block": 1.1675786658944698
      },
      {
        "layer": 4,
        "sigma_attn": 0.33165371568584057,
        "sigma_mlp": 0.5661622623265667,
        "sigma_block": 1.0995843754415873
      },
      {
        "layer": 5,
        "sigma_attn": 0.32354223493336565,
        "sigma_mlp": 0.6174690996092764,
        "sigma_block": 1.0664253634351382
      },
      {
        "layer": 6,
        "sigma_attn": 0.31320834744611625,
        "sigma_mlp": 0.5844582506535736,
        "sigma_block": 0.989121751977334
      },
      {
        "layer": 7,
        "sigma_attn": 0.3163919734801679,
        "sigma_mlp": 0.5715854538039841,
        "sigma_block": 0.9759301739531414
      },
      {
        "layer": 8,
        "sigma_attn": 0.26408961051966984,
        "sigma_mlp": 0.5275207426708791,
        "sigma_block": 0.9742127295757161
      },
      {
        "layer": 9,
        "sigma_attn": 0.30297738426997783,
        "sigma_mlp": 0.5416145459547362,
        "sigma_block": 0.9996982740892554
      },
      {
        "layer": 10,
        "sigma_attn": 0.3022375843323493,
        "sigma_mlp": 0.4862073238401024,
        "sigma_block": 1.020917812345465
      },
      {
        "layer": 11,
        "sigma_attn": 0.34877311529799404,
        "sigma_mlp": 0.5347642114494433,
        "sigma_block": 1.0938177214482703
      },
      {
        "layer": 12,
        "sigma_attn": 0.28862979953278134,
        "sigma_mlp": 0.5018610774328817,
        "sigma_block": 1.1115514895930159
      },
      {
        "layer": 13,
        "sigma_attn": 0.25779314075666304,
        "sigma_mlp": 0.5382613128946352,
        "sigma_block": 1.1401315127413467
      },
      {
        "layer": 14,
        "sigma_attn": 0.30199448198847395,
        "sigma_mlp": 0.5526727959921243,
        "sigma_block": 1.20276650912295
      },
      {
        "layer": 15,
        "sigma_attn": 0.21849192506699344,
        "sigma_mlp": 0.5691436734663207,
        "sigma_block": 1.2029725852071878
      }
    ]
  },
  "pythia-1.4b": {
    "num_layers": 24,
    "M": 72,
    "total_product": 1.1290050641125413e-09,
    "geomean": 0.7511590211966911,
    "median_sigma": 0.6092078313610505,
    "min_sigma": 0.2920811971410425,
    "max_sigma": 17.56101454860454,
    "num_below_1_5": 65,
    "product_below_1_5": 8.117168996004851e-14,
    "prod_attn": 3.3920939575976903e-06,
    "prod_mlp": 2.3894792681976807e-07,
    "prod_block": 1392.9154317823436,
    "gm_attn": 0.5917017150087666,
    "gm_mlp": 0.5297805007009884,
    "gm_block": 1.352062801837241,
    "per_layer": [
      {
        "layer": 0,
        "sigma_attn": 8.232305788646247,
        "sigma_mlp": 13.574806418426675,
        "sigma_block": 17.56101454860454
      },
      {
        "layer": 1,
        "sigma_attn": 0.4721818651277103,
        "sigma_mlp": 0.4607421698350252,
        "sigma_block": 1.1918395432595144
      },
      {
        "layer": 2,
        "sigma_attn": 0.2920811971410425,
        "sigma_mlp": 0.6381469632980259,
        "sigma_block": 1.2378479798447892
      },
      {
        "layer": 3,
        "sigma_attn": 0.3560425896428065,
        "sigma_mlp": 0.6395895049984675,
        "sigma_block": 1.1857829592752667
      },
      {
        "layer": 4,
        "sigma_attn": 0.32676521741424014,
        "sigma_mlp": 0.5997892977540424,
        "sigma_block": 1.1014246607977363
      },
      {
        "layer": 5,
        "sigma_attn": 0.3183926461263721,
        "sigma_mlp": 0.5845954799770995,
        "sigma_block": 1.052132348437787
      },
      {
        "layer": 6,
        "sigma_attn": 0.3167550178944544,
        "sigma_mlp": 0.5748241988193616,
        "sigma_block": 1.034032078297484
      },
      {
        "layer": 7,
        "sigma_attn": 0.33148638595735286,
        "sigma_mlp": 0.5442858338068259,
        "sigma_block": 1.0338187324287316
      },
      {
        "layer": 8,
        "sigma_attn": 0.3587673928195714,
        "sigma_mlp": 0.5248050118680203,
        "sigma_block": 0.995777641528916
      },
      {
        "layer": 9,
        "sigma_attn": 0.29212141280368814,
        "sigma_mlp": 0.49927099546173953,
        "sigma_block": 0.9837697966434226
      },
      {
        "layer": 10,
        "sigma_attn": 0.34155329271682006,
        "sigma_mlp": 0.5106052795570541,
        "sigma_block": 1.010531457790375
      },
      {
        "layer": 11,
        "sigma_attn": 0.6092078313610505,
        "sigma_mlp": 0.4881694685199137,
        "sigma_block": 1.13010707135711
      },
      {
        "layer": 12,
        "sigma_attn": 0.33515345358129045,
        "sigma_mlp": 0.45160503200206004,
        "sigma_block": 1.031677946504461
      },
      {
        "layer": 13,
        "sigma_attn": 0.6189554316054788,
        "sigma_mlp": 0.42322043980023266,
        "sigma_block": 1.1612303578674505
      },
      {
        "layer": 14,
        "sigma_attn": 0.5770369848274738,
        "sigma_mlp": 0.42463104294508647,
        "sigma_block": 1.1670441038046333
      },
      {
        "layer": 15,
        "sigma_attn": 1.1795546054857087,
        "sigma_mlp": 0.4113813938500444,
        "sigma_block": 1.5738388381557278
      },
      {
        "layer": 16,
        "sigma_attn": 0.556010844620053,
        "sigma_mlp": 0.3855596062606619,
        "sigma_block": 1.1913795122206086
      },
      {
        "layer": 17,
        "sigma_attn": 0.5847486334814032,
        "sigma_mlp": 0.35958918732242057,
        "sigma_block": 1.2051808299128153
      },
      {
        "layer": 18,
        "sigma_attn": 0.7383040078883326,
        "sigma_mlp": 0.3615588176038339,
        "sigma_block": 1.28984782249751
      },
      {
        "layer": 19,
        "sigma_attn": 0.5409725248730144,
        "sigma_mlp": 0.3597335384190452,
        "sigma_block": 1.1977575942658831
      },
      {
        "layer": 20,
        "sigma_attn": 1.155032462734511,
        "sigma_mlp": 0.35533084071845517,
        "sigma_block": 1.570654698308283
      },
      {
        "layer": 21,
        "sigma_attn": 1.0391768761295117,
        "sigma_mlp": 0.3469700661447561,
        "sigma_block": 1.4883664363674474
      },
      {
        "layer": 22,
        "sigma_attn": 1.33292410644727,
        "sigma_mlp": 0.3516950224068512,
        "sigma_block": 1.7140350596429428
      },
      {
        "layer": 23,
        "sigma_attn": 1.2007881301383576,
        "sigma_mlp": 0.5004402036732551,
        "sigma_block": 1.6727301439668683
      }
    ]
  },
  "pythia-2.8b": {
    "num_layers": 32,
    "M": 96,
    "total_product": 5.355427290530738e-19,
    "geomean": 0.6451711499142943,
    "median_sigma": 0.5268006041811704,
    "min_sigma": 0.26662598613268224,
    "max_sigma": 19.37330451361518,
    "num_below_1_5": 91,
    "product_below_1_5": 8.043282340125624e-23,
    "prod_attn": 1.4183120710060902e-10,
    "prod_mlp": 1.7456712520172688e-12,
    "prod_block": 2163.0166790687695,
    "gm_attn": 0.4923147738864473,
    "gm_mlp": 0.4291027787118986,
    "gm_block": 1.2712197187416863,
    "per_layer": [
      {
        "layer": 0,
        "sigma_attn": 8.507495292465595,
        "sigma_mlp": 14.520004287476358,
        "sigma_block": 19.37330451361518
      },
      {
        "layer": 1,
        "sigma_attn": 0.39579927317250885,
        "sigma_mlp": 0.3694418079175672,
        "sigma_block": 1.1113815768389017
      },
      {
        "layer": 2,
        "sigma_attn": 0.26662598613268224,
        "sigma_mlp": 0.5307725334131409,
        "sigma_block": 1.1808123847424257
      },
      {
        "layer": 3,
        "sigma_attn": 0.3609326097870016,
        "sigma_mlp": 0.5615769413414997,
        "sigma_block": 1.185942132500656
      },
      {
        "layer": 4,
        "sigma_attn": 0.3175513534127541,
        "sigma_mlp": 0.5243961475730367,
        "sigma_block": 1.100941269566489
      },
      {
        "layer": 5,
        "sigma_attn": 0.36115312285830037,
        "sigma_mlp": 0.5441870535770527,
        "sigma_block": 1.0715831713426236
      },
      {
        "layer": 6,
        "sigma_attn": 0.3191431225773341,
        "sigma_mlp": 0.5122426961389822,
        "sigma_block": 1.0774406553195806
      },
      {
        "layer": 7,
        "sigma_attn": 0.29217647840003197,
        "sigma_mlp": 0.4937426678457088,
        "sigma_block": 1.0568027016881225
      },
      {
        "layer": 8,
        "sigma_attn": 0.34627279026692187,
        "sigma_mlp": 0.4915228413582791,
        "sigma_block": 1.0423975038881368
      },
      {
        "layer": 9,
        "sigma_attn": 0.313733502588541,
        "sigma_mlp": 0.47072256008573704,
        "sigma_block": 1.021817601836614
      },
      {
        "layer": 10,
        "sigma_attn": 0.33383022770022674,
        "sigma_mlp": 0.4544864155495182,
        "sigma_block": 1.005284023343537
      },
      {
        "layer": 11,
        "sigma_attn": 0.31598674490462564,
        "sigma_mlp": 0.456513945680474,
        "sigma_block": 1.0132637111504863
      },
      {
        "layer": 12,
        "sigma_attn": 0.3049941004584696,
        "sigma_mlp": 0.42622980822819223,
        "sigma_block": 1.0304619268063058
      },
      {
        "layer": 13,
        "sigma_attn": 0.3262108193555686,
        "sigma_mlp": 0.4449629450438133,
        "sigma_block": 1.0228007192196862
      },
      {
        "layer": 14,
        "sigma_attn": 0.40734921195590434,
        "sigma_mlp": 0.4111987002395884,
        "sigma_block": 1.0549830842777852
      },
      {
        "layer": 15,
        "sigma_attn": 0.3042295849020209,
        "sigma_mlp": 0.39752431933677623,
        "sigma_block": 1.0563661757691083
      },
      {
        "layer": 16,
        "sigma_attn": 0.2696303974834525,
        "sigma_mlp": 0.38176668656214946,
        "sigma_block": 1.0418506010832451
      },
      {
        "layer": 17,
        "sigma_attn": 0.31383621447307297,
        "sigma_mlp": 0.3668499395598223,
        "sigma_block": 1.0761992683220014
      },
      {
        "layer": 18,
        "sigma_attn": 0.3074200973938146,
        "sigma_mlp": 0.34384999791358545,
        "sigma_block": 1.0815715259876229
      },
      {
        "layer": 19,
        "sigma_attn": 0.32838501324208424,
        "sigma_mlp": 0.3339713775887084,
        "sigma_block": 1.090741452224677
      },
      {
        "layer": 20,
        "sigma_attn": 0.42127959962926403,
        "sigma_mlp": 0.3247615292307975,
        "sigma_block": 1.13082655341278
      },
      {
        "layer": 21,
        "sigma_attn": 0.5268006041811704,
        "sigma_mlp": 0.31543437388080225,
        "sigma_block": 1.1751079506019448
      },
      {
        "layer": 22,
        "sigma_attn": 0.5606992483984241,
        "sigma_mlp": 0.3183361560221879,
        "sigma_block": 1.1936981829956808
      },
      {
        "layer": 23,
        "sigma_attn": 0.7582052862789881,
        "sigma_mlp": 0.29207499138432347,
        "sigma_block": 1.2962842598855981
      },
      {
        "layer": 24,
        "sigma_attn": 0.8054977554550984,
        "sigma_mlp": 0.29233881152565305,
        "sigma_block": 1.3215002770798439
      },
      {
        "layer": 25,
        "sigma_attn": 0.8877030111668383,
        "sigma_mlp": 0.28963075336686084,
        "sigma_block": 1.3736571807750155
      },
      {
        "layer": 26,
        "sigma_attn": 1.4504962210150363,
        "sigma_mlp": 0.28191035998335195,
        "sigma_block": 1.8014731427379147
      },
      {
        "layer": 27,
        "sigma_attn": 0.8620251666939552,
        "sigma_mlp": 0.2871444957385242,
        "sigma_block": 1.3583306719658867
      },
      {
        "layer": 28,
        "sigma_attn": 1.1170428462308695,
        "sigma_mlp": 0.28739431675278426,
        "sigma_block": 1.5444037760299005
      },
      {
        "layer": 29,
        "sigma_attn": 0.817823494746013,
        "sigma_mlp": 0.27608888705076007,
        "sigma_block": 1.3351096402232432
      },
      {
        "layer": 30,
        "sigma_attn": 0.8195885188301245,
        "sigma_mlp": 0.3119278283467985,
        "sigma_block": 1.3511451023402665
      },
      {
        "layer": 31,
        "sigma_attn": 0.5368879700953407,
        "sigma_mlp": 0.3911456131270646,
        "sigma_block": 1.2449956960953912
      }
    ]
  },
  "pythia-6.9b": {
    "num_layers": 32,
    "M": 96,
    "total_product": 3.105208082559447e-18,
    "geomean": 0.6570916446301884,
    "median_sigma": 0.6222241458072506,
    "min_sigma": 0.25027167076216345,
    "max_sigma": 21.496436385247573,
    "num_below_1_5": 86,
    "product_below_1_5": 2.2001795692329958e-23,
    "prod_attn": 9.190897428723757e-09,
    "prod_mlp": 2.0504526625873417e-14,
    "prod_block": 16477.18588190686,
    "gm_attn": 0.5608606035287068,
    "gm_mlp": 0.37346104200148045,
    "gm_block": 1.3544955889049353,
    "per_layer": [
      {
        "layer": 0,
        "sigma_attn": 8.474453524104849,
        "sigma_mlp": 16.425879748698794,
        "sigma_block": 21.496436385247573
      },
      {
        "layer": 1,
        "sigma_attn": 0.3509856675035336,
        "sigma_mlp": 0.2835661521828629,
        "sigma_block": 1.0822819727496111
      },
      {
        "layer": 2,
        "sigma_attn": 0.2709958872375233,
        "sigma_mlp": 0.48576788294816425,
        "sigma_block": 1.1548405403562758
      },
      {
        "layer": 3,
        "sigma_attn": 0.3203907208204087,
        "sigma_mlp": 0.4707213455351769,
        "sigma_block": 1.1429782239581918
      },
      {
        "layer": 4,
        "sigma_attn": 0.34100670013646905,
        "sigma_mlp": 0.4601375647037179,
        "sigma_block": 1.1531910341624887
      },
      {
        "layer": 5,
        "sigma_attn": 0.2829210098102017,
        "sigma_mlp": 0.44202492626455425,
        "sigma_block": 1.0970617161517056
      },
      {
        "layer": 6,
        "sigma_attn": 0.2782184594956383,
        "sigma_mlp": 0.41567099703621346,
        "sigma_block": 1.0616819677938785
      },
      {
        "layer": 7,
        "sigma_attn": 0.2735039259145029,
        "sigma_mlp": 0.412711585348286,
        "sigma_block": 1.0550195173149768
      },
      {
        "layer": 8,
        "sigma_attn": 0.267491260605903,
        "sigma_mlp": 0.417885813015688,
        "sigma_block": 1.0378360097642745
      },
      {
        "layer": 9,
        "sigma_attn": 0.27342654319612303,
        "sigma_mlp": 0.4136243117849882,
        "sigma_block": 1.0410094429126273
      },
      {
        "layer": 10,
        "sigma_attn": 0.2792592321851693,
        "sigma_mlp": 0.4032144300022111,
        "sigma_block": 1.023979185478191
      },
      {
        "layer": 11,
        "sigma_attn": 0.2548073098964979,
        "sigma_mlp": 0.38597769793842174,
        "sigma_block": 1.0316114844860507
      },
      {
        "layer": 12,
        "sigma_attn": 0.26999099433341694,
        "sigma_mlp": 0.3787693123076359,
        "sigma_block": 1.0399096367366152
      },
      {
        "layer": 13,
        "sigma_attn": 0.2833426630954242,
        "sigma_mlp": 0.37750286289492435,
        "sigma_block": 1.032536999148575
      },
      {
        "layer": 14,
        "sigma_attn": 0.2734121673294848,
        "sigma_mlp": 0.3566018505680824,
        "sigma_block": 1.0399803619966133
      },
      {
        "layer": 15,
        "sigma_attn": 0.3180726285747749,
        "sigma_mlp": 0.3444595570155146,
        "sigma_block": 1.0610772717127297
      },
      {
        "layer": 16,
        "sigma_attn": 0.32878200550793235,
        "sigma_mlp": 0.3302147881091084,
        "sigma_block": 1.0651893152400842
      },
      {
        "layer": 17,
        "sigma_attn": 0.5799291714256587,
        "sigma_mlp": 0.30754038233316494,
        "sigma_block": 1.1718442858459532
      },
      {
        "layer": 18,
        "sigma_attn": 0.6350601727611014,
        "sigma_mlp": 0.29318452614232904,
        "sigma_block": 1.197520954872428
      },
      {
        "layer": 19,
        "sigma_attn": 0.6222241458072506,
        "sigma_mlp": 0.28508738736724404,
        "sigma_block": 1.1972240432481471
      },
      {
        "layer": 20,
        "sigma_attn": 1.25439820103136,
        "sigma_mlp": 0.2738714665066917,
        "sigma_block": 1.6388370483951427
      },
      {
        "layer": 21,
        "sigma_attn": 1.6946709545160856,
        "sigma_mlp": 0.2624773560225602,
        "sigma_block": 2.000858017280105
      },
      {
        "layer": 22,
        "sigma_attn": 0.7319400218648192,
        "sigma_mlp": 0.2623131624402549,
        "sigma_block": 1.2655577639346651
      },
      {
        "layer": 23,
        "sigma_attn": 0.9144408891021694,
        "sigma_mlp": 0.25566281675687447,
        "sigma_block": 1.3853115585519318
      },
      {
        "layer": 24,
        "sigma_attn": 1.0692743332115078,
        "sigma_mlp": 0.25027167076216345,
        "sigma_block": 1.4960985215187526
      },
      {
        "layer": 25,
        "sigma_attn": 1.748112095128772,
        "sigma_mlp": 0.25440717986759215,
        "sigma_block": 2.0456552564873243
      },
      {
        "layer": 26,
        "sigma_attn": 1.028087363646217,
        "sigma_mlp": 0.25649208188314127,
        "sigma_block": 1.4640319700666964
      },
      {
        "layer": 27,
        "sigma_attn": 1.1360638251282833,
        "sigma_mlp": 0.2554021953166603,
        "sigma_block": 1.5764474064967018
      },
      {
        "layer": 28,
        "sigma_attn": 1.076650447983027,
        "sigma_mlp": 0.26015956280156544,
        "sigma_block": 1.5055914085889857
      },
      {
        "layer": 29,
        "sigma_attn": 0.9480052586891745,
        "sigma_mlp": 0.2578291441305973,
        "sigma_block": 1.4148594040290807
      },
      {
        "layer": 30,
        "sigma_attn": 0.8829441512621059,
        "sigma_mlp": 0.26010412278932077,
        "sigma_block": 1.3982914410280887
      },
      {
        "layer": 31,
        "sigma_attn": 0.6638270710732426,
        "sigma_mlp": 0.392158545645304,
        "sigma_block": 1.2935621649713036
      }
    ]
  },
  "pythia-12b": {
    "num_layers": 36,
    "M": 108,
    "total_product": 6.538733333201771e-23,
    "geomean": 0.62314326279574,
    "median_sigma": 0.6441321418369048,
    "min_sigma": 0.22692132809179721,
    "max_sigma": 25.298740529134975,
    "num_below_1_5": 101,
    "product_below_1_5": 1.9751778933968262e-27,
    "prod_attn": 1.0369416539026181e-09,
    "prod_mlp": 2.116720330415624e-18,
    "prod_block": 29790.365013945964,
    "gm_attn": 0.562908258129402,
    "gm_mlp": 0.3228837643397935,
    "gm_block": 1.3313121146679585,
    "per_layer": [
      {
        "layer": 0,
        "sigma_attn": 9.201721097407589,
        "sigma_mlp": 18.449784557719447,
        "sigma_block": 25.298740529134975
      },
      {
        "layer": 1,
        "sigma_attn": 0.3398087595064238,
        "sigma_mlp": 0.23620258464287405,
        "sigma_block": 1.0669094288167724
      },
      {
        "layer": 2,
        "sigma_attn": 0.3179544060670206,
        "sigma_mlp": 0.4046892718402913,
        "sigma_block": 1.1313706693311565
      },
      {
        "layer": 3,
        "sigma_attn": 0.28016974368395997,
        "sigma_mlp": 0.4269663126603823,
        "sigma_block": 1.119272644449882
      },
      {
        "layer": 4,
        "sigma_attn": 0.28013773439587897,
        "sigma_mlp": 0.3831366489146663,
        "sigma_block": 1.096051166004918
      },
      {
        "layer": 5,
        "sigma_attn": 0.24791389800433414,
        "sigma_mlp": 0.38059310137911645,
        "sigma_block": 1.075548854265761
      },
      {
        "layer": 6,
        "sigma_attn": 0.2524185882364819,
        "sigma_mlp": 0.3815278530923808,
        "sigma_block": 1.0617089492054466
      },
      {
        "layer": 7,
        "sigma_attn": 0.26772962517707366,
        "sigma_mlp": 0.37968708567329246,
        "sigma_block": 1.058938142417362
      },
      {
        "layer": 8,
        "sigma_attn": 0.27067457182559274,
        "sigma_mlp": 0.37442526036177187,
        "sigma_block": 1.0518971983527803
      },
      {
        "layer": 9,
        "sigma_attn": 0.2463818377975669,
        "sigma_mlp": 0.36593629075552847,
        "sigma_block": 1.0497220677086772
      },
      {
        "layer": 10,
        "sigma_attn": 0.25712793706302345,
        "sigma_mlp": 0.35679196235653676,
        "sigma_block": 1.0544030766178216
      },
      {
        "layer": 11,
        "sigma_attn": 0.2599870108832241,
        "sigma_mlp": 0.33904835739720235,
        "sigma_block": 1.046946267138887
      },
      {
        "layer": 12,
        "sigma_attn": 0.3298041244941879,
        "sigma_mlp": 0.3439619646450885,
        "sigma_block": 1.0629919157272216
      },
      {
        "layer": 13,
        "sigma_attn": 0.2752827062181455,
        "sigma_mlp": 0.32903075717580543,
        "sigma_block": 1.0502383221270581
      },
      {
        "layer": 14,
        "sigma_attn": 0.31139834257884924,
        "sigma_mlp": 0.32824424209100583,
        "sigma_block": 1.054676866535179
      },
      {
        "layer": 15,
        "sigma_attn": 0.39653566932903883,
        "sigma_mlp": 0.30370748275166864,
        "sigma_block": 1.0877605000657897
      },
      {
        "layer": 16,
        "sigma_attn": 0.5787908711662226,
        "sigma_mlp": 0.30161087883503856,
        "sigma_block": 1.1670411838730765
      },
      {
        "layer": 17,
        "sigma_attn": 0.6789942630850272,
        "sigma_mlp": 0.2768583309456989,
        "sigma_block": 1.223138154770242
      },
      {
        "layer": 18,
        "sigma_attn": 0.80433038265215,
        "sigma_mlp": 0.2801701309995667,
        "sigma_block": 1.2961175277249357
      },
      {
        "layer": 19,
        "sigma_attn": 0.6441321418369048,
        "sigma_mlp": 0.25783761673699956,
        "sigma_block": 1.2038802225057572
      },
      {
        "layer": 20,
        "sigma_attn": 1.1675719436366965,
        "sigma_mlp": 0.24664837881887203,
        "sigma_block": 1.5564229184509952
      },
      {
        "layer": 21,
        "sigma_attn": 0.8991814736171388,
        "sigma_mlp": 0.24901814865942812,
        "sigma_block": 1.3642893482386962
      },
      {
        "layer": 22,
        "sigma_attn": 0.7066374997209244,
        "sigma_mlp": 0.23816994572884234,
        "sigma_block": 1.248488451354817
      },
      {
        "layer": 23,
        "sigma_attn": 1.3322646870896138,
        "sigma_mlp": 0.2389874752845666,
        "sigma_block": 1.688435969701309
      },
      {
        "layer": 24,
        "sigma_attn": 1.0205315807188848,
        "sigma_mlp": 0.23221180475494868,
        "sigma_block": 1.4552573764326386
      },
      {
        "layer": 25,
        "sigma_attn": 1.060990641010802,
        "sigma_mlp": 0.23286824366502276,
        "sigma_block": 1.481670253630347
      },
      {
        "layer": 26,
        "sigma_attn": 0.89732820974124,
        "sigma_mlp": 0.2276685579280647,
        "sigma_block": 1.372211357158515
      },
      {
        "layer": 27,
        "sigma_attn": 0.9786542323410824,
        "sigma_mlp": 0.22823359517290412,
        "sigma_block": 1.4273635311516806
      },
      {
        "layer": 28,
        "sigma_attn": 1.2609246128354492,
        "sigma_mlp": 0.23543797897185006,
        "sigma_block": 1.6433123843065562
      },
      {
        "layer": 29,
        "sigma_attn": 1.4377322651657702,
        "sigma_mlp": 0.22692132809179721,
        "sigma_block": 1.7848256683357853
      },
      {
        "layer": 30,
        "sigma_attn": 0.8344161380362074,
        "sigma_mlp": 0.23016202777762396,
        "sigma_block": 1.3354785971921719
      },
      {
        "layer": 31,
        "sigma_attn": 0.7109172896578196,
        "sigma_mlp": 0.23183561172543365,
        "sigma_block": 1.262836271781029
      },
      {
        "layer": 32,
        "sigma_attn": 0.5691019102221243,
        "sigma_mlp": 0.2311233484190839,
        "sigma_block": 1.1929768112284385
      },
      {
        "layer": 33,
        "sigma_attn": 0.6872331997580885,
        "sigma_mlp": 0.23543029476802121,
        "sigma_block": 1.252813551935506
      },
      {
        "layer": 34,
        "sigma_attn": 0.39673839605131994,
        "sigma_mlp": 0.23281681730411075,
        "sigma_block": 1.1233866930010552
      },
      {
        "layer": 35,
        "sigma_attn": 0.49702974422314644,
        "sigma_mlp": 0.33254563841322893,
        "sigma_block": 1.204578526846376
      }
    ]
  },
  "Llama-2-7b-hf": {
    "num_layers": 32,
    "M": 96,
    "total_product": 1.357470246656957e-29,
    "geomean": 0.5003792296370502,
    "median_sigma": 0.49376675470774456,
    "min_sigma": 0.14898255609033345,
    "max_sigma": 3.537676851438601,
    "num_below_1_5": 94,
    "product_below_1_5": 1.2351786475996478e-30,
    "prod_attn": 2.5375246536511215e-21,
    "prod_mlp": 2.3240082022785856e-10,
    "prod_block": 23.01878478609963,
    "gm_attn": 0.22718927254727447,
    "gm_mlp": 0.4999711292138825,
    "gm_block": 1.1029734912209934,
    "per_layer": [
      {
        "layer": 0,
        "sigma_attn": 0.5064337448149661,
        "sigma_mlp": 0.7985174005707569,
        "sigma_block": 1.4998977339054176
      },
      {
        "layer": 1,
        "sigma_attn": 0.405680652084485,
        "sigma_mlp": 3.106578871014571,
        "sigma_block": 3.537676851438601
      },
      {
        "layer": 2,
        "sigma_attn": 0.2811382987626171,
        "sigma_mlp": 0.6787279707856805,
        "sigma_block": 1.1860864137376352
      },
      {
        "layer": 3,
        "sigma_attn": 0.3320767653360081,
        "sigma_mlp": 0.7198219871366753,
        "sigma_block": 1.1751327681420816
      },
      {
        "layer": 4,
        "sigma_attn": 0.29791398182079964,
        "sigma_mlp": 0.6992213884961065,
        "sigma_block": 1.1240947868868076
      },
      {
        "layer": 5,
        "sigma_attn": 0.2820817964692777,
        "sigma_mlp": 0.6470643222589417,
        "sigma_block": 1.0698782114795997
      },
      {
        "layer": 6,
        "sigma_attn": 0.29554924006429684,
        "sigma_mlp": 0.6509932291690881,
        "sigma_block": 1.039157235379195
      },
      {
        "layer": 7,
        "sigma_attn": 0.2953383710824831,
        "sigma_mlp": 0.641023660366906,
        "sigma_block": 1.0076588925437016
      },
      {
        "layer": 8,
        "sigma_attn": 0.28884142754841663,
        "sigma_mlp": 0.6007114035037051,
        "sigma_block": 0.9860994455041325
      },
      {
        "layer": 9,
        "sigma_attn": 0.28511378015055533,
        "sigma_mlp": 0.57701281553695,
        "sigma_block": 0.9815320494870964
      },
      {
        "layer": 10,
        "sigma_attn": 0.29453602028842046,
        "sigma_mlp": 0.534662918879986,
        "sigma_block": 0.9621928371218436
      },
      {
        "layer": 11,
        "sigma_attn": 0.2734749323137303,
        "sigma_mlp": 0.52615720105855,
        "sigma_block": 0.9514923209255108
      },
      {
        "layer": 12,
        "sigma_attn": 0.258263920781231,
        "sigma_mlp": 0.5087457417505806,
        "sigma_block": 0.9594309792242267
      },
      {
        "layer": 13,
        "sigma_attn": 0.24894163314488876,
        "sigma_mlp": 0.49376675470774456,
        "sigma_block": 0.9427178303127091
      },
      {
        "layer": 14,
        "sigma_attn": 0.2527210687608602,
        "sigma_mlp": 0.47896723121033846,
        "sigma_block": 0.9542208682617559
      },
      {
        "layer": 15,
        "sigma_attn": 0.25585513022162654,
        "sigma_mlp": 0.4752236227290198,
        "sigma_block": 0.9627362000522803
      },
      {
        "layer": 16,
        "sigma_attn": 0.2526791977289694,
        "sigma_mlp": 0.4606630094048746,
        "sigma_block": 0.9846746834605113
      },
      {
        "layer": 17,
        "sigma_attn": 0.21798402356772253,
        "sigma_mlp": 0.42956012302273355,
        "sigma_block": 0.9926537080356775
      },
      {
        "layer": 18,
        "sigma_attn": 0.19274559233732041,
        "sigma_mlp": 0.4109779635819396,
        "sigma_block": 1.0164780254338328
      },
      {
        "layer": 19,
        "sigma_attn": 0.1744628067788654,
        "sigma_mlp": 0.38986332145644276,
        "sigma_block": 1.0327548546968202
      },
      {
        "layer": 20,
        "sigma_attn": 0.1685260435367341,
        "sigma_mlp": 0.37636804874381424,
        "sigma_block": 1.0463632505410092
      },
      {
        "layer": 21,
        "sigma_attn": 0.1512675610107384,
        "sigma_mlp": 0.35627082557517964,
        "sigma_block": 1.0565582008657741
      },
      {
        "layer": 22,
        "sigma_attn": 0.16884198328853497,
        "sigma_mlp": 0.3427366494565312,
        "sigma_block": 1.0684039304183817
      },
      {
        "layer": 23,
        "sigma_attn": 0.14898255609033345,
        "sigma_mlp": 0.33344150679494394,
        "sigma_block": 1.070547321625702
      },
      {
        "layer": 24,
        "sigma_attn": 0.16032069271928034,
        "sigma_mlp": 0.32470307037139806,
        "sigma_block": 1.0776787888461095
      },
      {
        "layer": 25,
        "sigma_attn": 0.15550139850336997,
        "sigma_mlp": 0.3249007499189934,
        "sigma_block": 1.082163059793255
      },
      {
        "layer": 26,
        "sigma_attn": 0.15870397021815633,
        "sigma_mlp": 0.3215608024476542,
        "sigma_block": 1.0888101579509621
      },
      {
        "layer": 27,
        "sigma_attn": 0.1593482054171917,
        "sigma_mlp": 0.32492224307981676,
        "sigma_block": 1.0895261799261589
      },
      {
        "layer": 28,
        "sigma_attn": 0.16821409158948583,
        "sigma_mlp": 0.33581434540581845,
        "sigma_block": 1.099203552326204
      },
      {
        "layer": 29,
        "sigma_attn": 0.15448407048092855,
        "sigma_mlp": 0.34665877655144994,
        "sigma_block": 1.1038719203579583
      },
      {
        "layer": 30,
        "sigma_attn": 0.17265801254500285,
        "sigma_mlp": 0.3885733891912577,
        "sigma_block": 1.1263112579427084
      },
      {
        "layer": 31,
        "sigma_attn": 0.1946690279516734,
        "sigma_mlp": 0.7519663139486361,
        "sigma_block": 1.3683361930691196
      }
    ]
  }
}